{"timestamp":1772222100744,"date":"2026-02-27T19:55:00.744Z","models":{"moonshot/kimi-k2.5":{"name":"Moonshot Kimi K2.5 (Primary - ALL BOTS)","dailyUsed":17702,"monthlySpent":96.01615644696302,"dailyCost":3.200538548232101},"kimi-coding/k2p5":{"name":"Kimi Code K2.5 (Sub-agent - ALL BOTS)","dailyUsed":18642,"monthlySpent":89.85048116532315,"dailyCost":2.995016038844105},"minimax/MiniMax-M2.1":{"name":"MiniMax M2.1 (Coding)","dailyUsed":15827,"monthlySpent":79.84458024247496,"dailyCost":2.6614860080824987}}}