{"timestamp":1772186100829,"date":"2026-02-27T09:55:00.829Z","models":{"moonshot/kimi-k2.5":{"name":"Moonshot Kimi K2.5 (Primary - ALL BOTS)","dailyUsed":13554,"monthlySpent":73.7310203267697,"dailyCost":2.45770067755899},"kimi-coding/k2p5":{"name":"Kimi Code K2.5 (Sub-agent - ALL BOTS)","dailyUsed":14609,"monthlySpent":71.24684745911071,"dailyCost":2.3748949153036905},"minimax/MiniMax-M2.1":{"name":"MiniMax M2.1 (Coding)","dailyUsed":12008,"monthlySpent":59.1020028172353,"dailyCost":1.9700667605745101}}}