{
  "search_metadata": {
    "date": "2026-04-07",
    "query": "CNC machine shops in Florida",
    "target_count": "20-25 shops",
    "actual_count": 25,
    "search_date": "2026-04-11"
  },
  "shops": [
    {
      "id": 1,
      "name": "CJ Manufacturing",
      "location": "Florida",
      "address": null,
      "phone": null,
      "email": null,
      "website": "http://www.floridacncmachining.com/",
      "services": ["Precision CNC Milling & Turning", "Precision Sheet-Metal Fabrication", "In-House Component Assembly and Finishing", "Assemblies", "Low & High Volume Runs"],
      "certifications": ["AS9100D", "Cage Code - 13JV2", "UEI - XGPUAYWMFDF3", "DUNS - 137729662"],
      "materials": ["Aluminum", "Steel", "Titanium", "Stainless Steel", "Plastics"],
      "notes": "Family owned and operated with over 30 years of experience. Certified Aerospace Supplier."
    },
    {
      "id": 2,
      "name": "Mill It Now.com (NCAD Products, Inc.)",
      "location": "Oviedo, FL",
      "address": "Oviedo, FL",
      "phone": "855-288-1669",
      "email": null,
      "website": "https://millitnow.com",
      "services": ["Rapid CNC Milling Services", "CNC Machining"],
      "certifications": [],
      "materials": [],
      "notes": "Division of NCAD Products, Inc. specifically designed to offer rapid CNC milling services."
    },
    {
      "id": 3,
      "name": "CNC Fabrication Florida (Artistic Contractors Inc.)",
      "location": "Atlantic Beach, FL",
      "address": "1850 Mealy St S, Atlantic Beach, FL 32233",
      "phone": "(904) 853-6853",
      "email": null,
      "website": "https://cncfabricationfl.com/",
      "services": ["Custom CNC Machining", "CNC Routing", "CNC Milling", "Crown Molding Designs", "CNC Cutting", "Machining for Decorative Projects", "CNC Woodworking", "Custom CAD Drawings"],
      "certifications": [],
      "materials": [],
      "notes": "Over 15 years of experience. Division of Artistic Contractors Inc. M-F: 8:30am – 5pm."
    },
    {
      "id": 4,
      "name": "CLN of South Florida",
      "location": "Belle Glade, FL",
      "address": "2336 Cypress Ln, Belle Glade, FL 33430",
      "phone": "561-944-3363",
      "email": null,
      "website": "https://clnofsouthflorida.com/",
      "services": ["CNC Machining Services", "Prototyping", "One-off Parts", "Large-scale Production"],
      "certifications": [],
      "materials": [],
      "notes": "Serving aerospace, automotive, medical industries. Made in the USA machines."
    },
    {
      "id": 5,
      "name": "Distinctive Manufacturing Group",
      "location": "Miami, FL (serves all of Florida)",
      "address": null,
      "phone": "616-953-8999",
      "email": null,
      "website": "https://distinctivemfg.co/",
      "services": ["CNC Machining", "Metal Fabrication", "CNC Milling", "CNC Turning", "5-Axis CNC Machining", "Prototyping", "3D Printing", "Welding"],
      "certifications": [],
      "materials": ["Titanium", "Brass", "Copper Alloys", "Aluminum", "Alloy Steel", "Stainless Steel", "Inconel", "Plastics (Nylon, Delrin, PVC)", "Steel"],
      "notes": "Serves Miami, Jacksonville, Tampa, Orlando. Can handle weldments up to 40,000+ pounds."
    },
    {
      "id": 6,
      "name": "RAM Tool, Inc.",
      "location": "Grafton, WI (serves all of Florida)",
      "address": "Grafton, WI",
      "phone": null,
      "email": null,
      "website": "https://www.ramtoolinc.com/",
      "services": ["Precision CNC Machining", "Contract Milling", "Prototype Tooling", "Die Cast Dies", "Laser Scanning", "Custom Inspection", "EDM Services"],
      "certifications": [],
      "materials": ["Stainless Steel 15-5", "17-4", "304", "316", "420", "Titanium Ti-6Al-4V (Grade 5)"],
      "notes": "Serving Florida since 1979. 80,000 sq ft facility. 16 machining centers. Serves Jacksonville, Miami, Tampa, Orlando, St. Petersburg, Tallahassee."
    },
    {
      "id": 7,
      "name": "Blanda, Inc.",
      "location": "Minneapolis, MN (serves all of Florida)",
      "address": "Minneapolis, MN",
      "phone": "(651) 688-9510",
      "email": null,
      "website": "https://blanda.net/",
      "services": ["CNC Machining", "Wire EDM", "Prototyping", "Waterjet Cutting", "Precision Grinding", "5-Axis Machining"],
      "certifications": [],
      "materials": ["Stainless Steel", "Titanium", "Hot Rolled Steel", "Cold Rolled Steel", "All Alloys", "Plastics (PEEK, Nylon, PVC, ABS, Delrin)", "Copper", "Brass", "Bronze", "Monel", "Inconel"],
      "notes": "Serving St. Petersburg, Orlando, Clearwater, Palm Harbor since 1979."
    },
    {
      "id": 8,
      "name": "Roberson Machine Company",
      "location": "Missouri (serves Orlando, FL)",
      "address": null,
      "phone": "573-646-3996",
      "email": null,
      "website": "https://robersontool.com/",
      "services": ["CNC Services", "Precision Machining", "Metal Fabrication", "Prototyping", "Welding", "3D Printing", "Assembly", "CNC Turning", "CNC Milling", "CNC EDM", "CNC Laser Machining", "CNC Plasma Cutting"],
      "certifications": [],
      "materials": [],
      "notes": "Serves Orlando, FL area. Single-source machine shop."
    },
    {
      "id": 9,
      "name": "Catamount Machine Works",
      "location": "Plant City, FL",
      "address": "2804 Sydney Road, Plant City, FL 33566",
      "phone": "813-659-0505",
      "email": "info@catmw.com",
      "website": "https://catmw.com/",
      "services": ["5-Axis CNC Machining", "3-Axis CNC Machining", "4-Axis CNC Machining", "CNC Mills", "CNC Lathes", "Wire EDM", "Rapid Prototyping", "Robotics & Automation", "CAD Engineering", "Turnkey Manufacturing"],
      "certifications": ["AS9100 Certified", "ITAR Registered", "JCP Certified", "CMMC 2.0 Compliant"],
      "materials": ["Metal", "Composite Materials", "Titanium", "Hastelloy", "Kovar", "Inconel"],
      "notes": "Founded in 2005. Serves Miami, Tampa, Daytona, Tallahassee, Orlando. Business Hours: M-F 8:00 AM - 5:00 PM EST."
    },
    {
      "id": 10,
      "name": "JW Machine Corporation",
      "location": "Orlando, FL",
      "address": "2525 Industrial Boulevard, Orlando, FL 32804",
      "phone": "407-298-9171",
      "email": null,
      "website": "https://jwmachinecorp.com/",
      "services": ["Close Tolerance & Small Part Machining", "Multi-Axis Milling and Turning", "Machining Center Production", "CAD Design Assistance", "Engineering", "Prototypes to Production Manufacturing", "Component Part Inserts and Assembly", "Laser Cutting and Engraving", "Metal Finishing"],
      "certifications": ["AS 9100 D", "ISO 9001:2015", "ITAR Compliant"],
      "materials": ["All Materials", "Exotics", "Plastics"],
      "notes": "Central Florida's leading precision CNC shop. Work sizes from .03\" dia. to 12.00\" dia. (round) to 20\" x 44\" (square). Tolerances to ±.0001."
    },
    {
      "id": 11,
      "name": "Owens Industries, LLC",
      "location": "Wisconsin (serves Florida)",
      "address": null,
      "phone": null,
      "email": null,
      "website": "https://www.owensind.com/",
      "services": ["Ultra-precision CNC Machining", "5-Axis Wire EDM", "CNC Turning", "CNC Milling", "Deburring"],
      "certifications": [],
      "materials": [],
      "notes": "Ultra-precision CNC machine shop specializing in simultaneous 5-axis wire EDM."
    },
    {
      "id": 12,
      "name": "AT Precision",
      "location": "Illinois (serves Tampa, FL)",
      "address": null,
      "phone": "(847) 509-5848",
      "email": null,
      "website": "https://www.atprecision.com/",
      "services": ["CNC Machining Services"],
      "certifications": [],
      "materials": [],
      "notes": "CNC machine shop serving Tampa, Florida."
    },
    {
      "id": 13,
      "name": "Mahuta Tool Corporation",
      "location": null,
      "address": null,
      "phone": null,
      "email": null,
      "website": "https://www.mahutatool.com/",
      "services": ["CNC Machining", "Tool & Die Services"],
      "certifications": [],
      "materials": [],
      "notes": "Provides CNC machining and tool & die services throughout Florida from Jacksonville to Miami to Tampa."
    },
    {
      "id": 14,
      "name": "Accurate Machine & Tool Inc",
      "location": "Miami, FL",
      "address": "4555 Northwest 73rd Avenue, Miami, FL 33166-6438",
      "phone": "(305) 592-2457",
      "email": null,
      "website": null,
      "services": ["CNC Machine Shop"],
      "certifications": [],
      "materials": [],
      "notes": "Contact: Miroslav Tasev (President)"
    },
    {
      "id": 15,
      "name": "Al M Machine Inc",
      "location": "Miami, FL",
      "address": "4585 Northwest 37th Avenue, Miami, FL 33142-4229",
      "phone": "(305) 637-4435",
      "email": null,
      "website": null,
      "services": ["CNC Machine Shop"],
      "certifications": [],
      "materials": [],
      "notes": ""
    },
    {
      "id": 16,
      "name": "Amador Machine Shop Inc",
      "location": "Miami, FL",
      "address": "2421 Northwest 27th Avenue, Miami, FL 33142-7233",
      "phone": null,
      "email": null,
      "website": null,
      "services": ["CNC Machine Shop"],
      "certifications": [],
      "materials": [],
      "notes": "Contact: Miguel Valdes (President)"
    },
    {
      "id": 17,
      "name": "Associated Machine Co Inc",
      "location": "Miami, FL",
      "address": "6540 Northwest 35th Avenue, Miami, FL 33147-7563",
      "phone": "(305) 836-6163",
      "email": null,
      "website": null,
      "services": ["CNC Machine Shop"],
      "certifications": [],
      "materials": [],
      "notes": "Contact: Evelyn Wade (Customer Service)"
    },
    {
      "id": 18,
      "name": "Bird Road Machine Shop",
      "location": "Miami, FL",
      "address": "7120 Southwest 44th Street, Miami, FL 33155-4638",
      "phone": "(305) 669-0505",
      "email": null,
      "website": null,
      "services": ["CNC Machine Shop"],
      "certifications": [],
      "materials": [],
      "notes": ""
    },
    {
      "id": 19,
      "name": "Caudle Manufacturing Co",
      "location": "Miami, FL",
      "address": "7545 Northwest 26th Avenue, Miami, FL 33147-6003",
      "phone": null,
      "email": null,
      "website": null,
      "services": ["CNC Machine Shop", "Castings Industrial", "Die Casting", "Assembly", "Machining", "Maintenance", "Manufacturing"],
      "certifications": [],
      "materials": [],
      "notes": "Contact: Frank Caudle (Owner). Products: Pallets, Dies, Tooling, Molds, Zinc, Tools, Fixtures, Drills, Trim, Parts"
    },
    {
      "id": 20,
      "name": "Chavez Machine Shop",
      "location": "Miami, FL",
      "address": "5310 Northwest 32nd Avenue, Miami, FL 33142-3302",
      "phone": "(305) 634-2723",
      "email": null,
      "website": null,
      "services": ["CNC Machine Shop"],
      "certifications": [],
      "materials": [],
      "notes": "Contact: Miguel Chavez (Owner)"
    },
    {
      "id": 21,
      "name": "Kendall Machine Shop Inc",
      "location": "Miami, FL",
      "address": "12500 Southwest 130th Street Suite 20, Miami, FL 33186-6223",
      "phone": "(305) 235-3393",
      "email": null,
      "website": null,
      "services": ["CNC Machine Shop"],
      "certifications": [],
      "materials": [],
      "notes": "Contact: Dennis Moncada (President)"
    },
    {
      "id": 22,
      "name": "Metro Machine Co Inc",
      "location": "Miami, FL",
      "address": "7886 Northwest 64th Street, Miami, FL 33166-2706",
      "phone": "(305) 591-4498",
      "email": null,
      "website": null,
      "services": ["CNC Machine Shop"],
      "certifications": [],
      "materials": [],
      "notes": ""
    },
    {
      "id": 23,
      "name": "South Florida Machine",
      "location": "Miami, FL",
      "address": "7301 Southwest 45th Street, Miami, FL 33155-4533",
      "phone": "(305) 266-7900",
      "email": null,
      "website": null,
      "services": ["CNC Machine Shop", "Machine Shop", "Rebuild Engines", "Rebuilding", "Motor Rebuilding", "Remanufactured"],
      "certifications": [],
      "materials": [],
      "notes": "Contact: Patrick Cugno. Products: Custom Engines"
    },
    {
      "id": 24,
      "name": "Victores Machine Shop",
      "location": "Miami, FL",
      "address": "5720 Northwest 35th Avenue, Miami, FL 33142-2708",
      "phone": "(305) 635-0219",
      "email": null,
      "website": null,
      "services": ["CNC Machine Shop"],
      "certifications": [],
      "materials": [],
      "notes": "Contact: Jesus Victores (Owner)"
    },
    {
      "id": 25,
      "name": "Zee's Repair Service",
      "location": "Miami, FL",
      "address": "2235 Northwest 41st Street, Miami, FL 33142-4623",
      "phone": "(305) 635-7902",
      "email": null,
      "website": null,
      "services": ["CNC Machine Shop"],
      "certifications": [],
      "materials": [],
      "notes": "Contact: Jim Houghton (Owner)"
    }
  ],
  "statistics": {
    "by_city": {
      "Miami": 14,
      "Orlando": 2,
      "Plant City": 1,
      "Atlantic Beach": 1,
      "Belle Glade": 1,
      "Oviedo": 1,
      "Other/Multi-location": 5
    },
    "with_phone": 20,
    "with_email": 2,
    "with_website": 15,
    "certified_shops": 4
  }
}