{"timestamp":1772118300838,"date":"2026-02-26T15:05:00.838Z","models":{"moonshot/kimi-k2.5":{"name":"Moonshot Kimi K2.5 (Primary - ALL BOTS)","dailyUsed":6089,"monthlySpent":37.52759319548254,"dailyCost":1.2509197731827513},"kimi-coding/k2p5":{"name":"Kimi Code K2.5 (Sub-agent - ALL BOTS)","dailyUsed":7020,"monthlySpent":32.870145679309424,"dailyCost":1.0956715226436475},"minimax/MiniMax-M2.1":{"name":"MiniMax M2.1 (Coding)","dailyUsed":4598,"monthlySpent":20.708146425777898,"dailyCost":0.6902715475259299}}}