{"timestamp":1772243700503,"date":"2026-02-28T01:55:00.503Z","models":{"moonshot/kimi-k2.5":{"name":"Moonshot Kimi K2.5 (Primary - ALL BOTS)","dailyUsed":20032,"monthlySpent":105.9645474410894,"dailyCost":3.5321515813696465},"kimi-coding/k2p5":{"name":"Kimi Code K2.5 (Sub-agent - ALL BOTS)","dailyUsed":20466,"monthlySpent":100.19333399413685,"dailyCost":3.3397777998045615},"minimax/MiniMax-M2.1":{"name":"MiniMax M2.1 (Coding)","dailyUsed":17527,"monthlySpent":88.88881901695989,"dailyCost":2.9629606338986627}}}