{"timestamp":1773392100466,"date":"2026-03-13T08:55:00.466Z","models":{"moonshot/kimi-k2.5":{"name":"Moonshot Kimi K2.5 (Primary - ALL BOTS)","dailyUsed":147655,"monthlySpent":745.6898590189811,"dailyCost":24.856328633966037},"kimi-coding/k2p5":{"name":"Kimi Code K2.5 (Sub-agent - ALL BOTS)","dailyUsed":149098,"monthlySpent":733.0490666824758,"dailyCost":24.43496888941586},"minimax/MiniMax-M2.1":{"name":"MiniMax M2.1 (Coding)","dailyUsed":144946,"monthlySpent":719.4800262596972,"dailyCost":23.982667541989905}}}