{"timestamp":1774204800510,"date":"2026-03-22T18:40:00.510Z","models":{"moonshot/kimi-k2.5":{"name":"Moonshot Kimi K2.5 (Primary - ALL BOTS)","dailyUsed":236886,"monthlySpent":1195.307278401151,"dailyCost":39.84357594670504},"kimi-coding/k2p5":{"name":"Kimi Code K2.5 (Sub-agent - ALL BOTS)","dailyUsed":239526,"monthlySpent":1186.3231912272672,"dailyCost":39.54410637424224},"minimax/MiniMax-M2.1":{"name":"MiniMax M2.1 (Coding)","dailyUsed":236235,"monthlySpent":1165.5827978210505,"dailyCost":38.852759927368346}}}