{"timestamp":1773529500906,"date":"2026-03-14T23:05:00.906Z","models":{"moonshot/kimi-k2.5":{"name":"Moonshot Kimi K2.5 (Primary - ALL BOTS)","dailyUsed":162125,"monthlySpent":823.5535376041362,"dailyCost":27.45178458680454},"kimi-coding/k2p5":{"name":"Kimi Code K2.5 (Sub-agent - ALL BOTS)","dailyUsed":163840,"monthlySpent":811.3848552043984,"dailyCost":27.046161840146613},"minimax/MiniMax-M2.1":{"name":"MiniMax M2.1 (Coding)","dailyUsed":159790,"monthlySpent":795.4430437417172,"dailyCost":26.514768124723908}}}