{"timestamp":1773019500035,"date":"2026-03-09T01:25:00.035Z","models":{"moonshot/kimi-k2.5":{"name":"Moonshot Kimi K2.5 (Primary - ALL BOTS)","dailyUsed":106209,"monthlySpent":539.6900884119362,"dailyCost":17.98966961373121},"kimi-coding/k2p5":{"name":"Kimi Code K2.5 (Sub-agent - ALL BOTS)","dailyUsed":107422,"monthlySpent":525.2848077367931,"dailyCost":17.509493591226438},"minimax/MiniMax-M2.1":{"name":"MiniMax M2.1 (Coding)","dailyUsed":103511,"monthlySpent":514.6364909113726,"dailyCost":17.154549697045752}}}