{"timestamp":1772704500967,"date":"2026-03-05T09:55:00.967Z","models":{"moonshot/kimi-k2.5":{"name":"Moonshot Kimi K2.5 (Primary - ALL BOTS)","dailyUsed":71235,"monthlySpent":363.0404008260701,"dailyCost":12.101346694202336},"kimi-coding/k2p5":{"name":"Kimi Code K2.5 (Sub-agent - ALL BOTS)","dailyUsed":72797,"monthlySpent":355.5222424865632,"dailyCost":11.850741416218773},"minimax/MiniMax-M2.1":{"name":"MiniMax M2.1 (Coding)","dailyUsed":69780,"monthlySpent":343.55126709675835,"dailyCost":11.451708903225278}}}