{"timestamp":1773436800052,"date":"2026-03-13T21:20:00.052Z","models":{"moonshot/kimi-k2.5":{"name":"Moonshot Kimi K2.5 (Primary - ALL BOTS)","dailyUsed":152365,"monthlySpent":771.1939896537609,"dailyCost":25.706466321792032},"kimi-coding/k2p5":{"name":"Kimi Code K2.5 (Sub-agent - ALL BOTS)","dailyUsed":154104,"monthlySpent":760.2559975689759,"dailyCost":25.34186658563253},"minimax/MiniMax-M2.1":{"name":"MiniMax M2.1 (Coding)","dailyUsed":149893,"monthlySpent":743.43621466549,"dailyCost":24.78120715551633}}}