{"timestamp":1773387600264,"date":"2026-03-13T07:40:00.264Z","models":{"moonshot/kimi-k2.5":{"name":"Moonshot Kimi K2.5 (Primary - ALL BOTS)","dailyUsed":147121,"monthlySpent":742.7982287684117,"dailyCost":24.75994095894706},"kimi-coding/k2p5":{"name":"Kimi Code K2.5 (Sub-agent - ALL BOTS)","dailyUsed":148711,"monthlySpent":730.5679163784451,"dailyCost":24.352263879281505},"minimax/MiniMax-M2.1":{"name":"MiniMax M2.1 (Coding)","dailyUsed":144425,"monthlySpent":716.7353908455661,"dailyCost":23.891179694852205}}}