{"timestamp":1772831100075,"date":"2026-03-06T21:05:00.075Z","models":{"moonshot/kimi-k2.5":{"name":"Moonshot Kimi K2.5 (Primary - ALL BOTS)","dailyUsed":84533,"monthlySpent":433.68647461780154,"dailyCost":14.456215820593384},"kimi-coding/k2p5":{"name":"Kimi Code K2.5 (Sub-agent - ALL BOTS)","dailyUsed":85852,"monthlySpent":419.4188621969622,"dailyCost":13.98062873989874},"minimax/MiniMax-M2.1":{"name":"MiniMax M2.1 (Coding)","dailyUsed":82903,"monthlySpent":411.3584345294601,"dailyCost":13.71194781764867}}}