{"timestamp":1773456900722,"date":"2026-03-14T02:55:00.722Z","models":{"moonshot/kimi-k2.5":{"name":"Moonshot Kimi K2.5 (Primary - ALL BOTS)","dailyUsed":154212,"monthlySpent":782.9227398653898,"dailyCost":26.09742466217966},"kimi-coding/k2p5":{"name":"Kimi Code K2.5 (Sub-agent - ALL BOTS)","dailyUsed":156567,"monthlySpent":771.312515892155,"dailyCost":25.710417196405167},"minimax/MiniMax-M2.1":{"name":"MiniMax M2.1 (Coding)","dailyUsed":151619,"monthlySpent":756.3355874537697,"dailyCost":25.21118624845899}}}