{"timestamp":1773507900251,"date":"2026-03-14T17:05:00.251Z","models":{"moonshot/kimi-k2.5":{"name":"Moonshot Kimi K2.5 (Primary - ALL BOTS)","dailyUsed":159527,"monthlySpent":813.0195103744,"dailyCost":27.100650345813335},"kimi-coding/k2p5":{"name":"Kimi Code K2.5 (Sub-agent - ALL BOTS)","dailyUsed":161722,"monthlySpent":801.1518989936513,"dailyCost":26.705063299788378},"minimax/MiniMax-M2.1":{"name":"MiniMax M2.1 (Coding)","dailyUsed":157395,"monthlySpent":784.3225362926954,"dailyCost":26.144084543089846}}}