{"timestamp":1774158600166,"date":"2026-03-22T05:50:00.166Z","models":{"moonshot/kimi-k2.5":{"name":"Moonshot Kimi K2.5 (Primary - ALL BOTS)","dailyUsed":231827,"monthlySpent":1169.2623582382937,"dailyCost":38.975411941276455},"kimi-coding/k2p5":{"name":"Kimi Code K2.5 (Sub-agent - ALL BOTS)","dailyUsed":234460,"monthlySpent":1158.2587368754896,"dailyCost":38.60862456251632},"minimax/MiniMax-M2.1":{"name":"MiniMax M2.1 (Coding)","dailyUsed":231102,"monthlySpent":1138.7958456219574,"dailyCost":37.95986152073191}}}