{"timestamp":1772483100575,"date":"2026-03-02T20:25:00.575Z","models":{"moonshot/kimi-k2.5":{"name":"Moonshot Kimi K2.5 (Primary - ALL BOTS)","dailyUsed":46828,"monthlySpent":241.07877719090303,"dailyCost":8.035959239696767},"kimi-coding/k2p5":{"name":"Kimi Code K2.5 (Sub-agent - ALL BOTS)","dailyUsed":47824,"monthlySpent":237.20206197769852,"dailyCost":7.906735399256617},"minimax/MiniMax-M2.1":{"name":"MiniMax M2.1 (Coding)","dailyUsed":44774,"monthlySpent":220.5724532597949,"dailyCost":7.35241510865983}}}