{"timestamp":1773187800601,"date":"2026-03-11T00:10:00.601Z","models":{"moonshot/kimi-k2.5":{"name":"Moonshot Kimi K2.5 (Primary - ALL BOTS)","dailyUsed":125050,"monthlySpent":636.0772981391517,"dailyCost":21.20257660463839},"kimi-coding/k2p5":{"name":"Kimi Code K2.5 (Sub-agent - ALL BOTS)","dailyUsed":126243,"monthlySpent":616.9898531147853,"dailyCost":20.56632843715951},"minimax/MiniMax-M2.1":{"name":"MiniMax M2.1 (Coding)","dailyUsed":121932,"monthlySpent":605.2629419247569,"dailyCost":20.175431397491895}}}