{"timestamp":1773137100107,"date":"2026-03-10T10:05:00.107Z","models":{"moonshot/kimi-k2.5":{"name":"Moonshot Kimi K2.5 (Primary - ALL BOTS)","dailyUsed":119771,"monthlySpent":605.5092009995819,"dailyCost":20.1836400333194},"kimi-coding/k2p5":{"name":"Kimi Code K2.5 (Sub-agent - ALL BOTS)","dailyUsed":119808,"monthlySpent":589.8388572154121,"dailyCost":19.661295240513734},"minimax/MiniMax-M2.1":{"name":"MiniMax M2.1 (Coding)","dailyUsed":116155,"monthlySpent":576.8572656342578,"dailyCost":19.228575521141927}}}