{"timestamp":1774208400411,"date":"2026-03-22T19:40:00.411Z","models":{"moonshot/kimi-k2.5":{"name":"Moonshot Kimi K2.5 (Primary - ALL BOTS)","dailyUsed":237282,"monthlySpent":1196.7954615875976,"dailyCost":39.89318205291992},"kimi-coding/k2p5":{"name":"Kimi Code K2.5 (Sub-agent - ALL BOTS)","dailyUsed":239923,"monthlySpent":1188.713127203869,"dailyCost":39.62377090679563},"minimax/MiniMax-M2.1":{"name":"MiniMax M2.1 (Coding)","dailyUsed":236635,"monthlySpent":1167.730932983572,"dailyCost":38.92436443278574}}}