{"timestamp":1773001500243,"date":"2026-03-08T20:25:00.243Z","models":{"moonshot/kimi-k2.5":{"name":"Moonshot Kimi K2.5 (Primary - ALL BOTS)","dailyUsed":103989,"monthlySpent":529.8317793058119,"dailyCost":17.66105931019373},"kimi-coding/k2p5":{"name":"Kimi Code K2.5 (Sub-agent - ALL BOTS)","dailyUsed":105197,"monthlySpent":515.0301680124371,"dailyCost":17.167672267081237},"minimax/MiniMax-M2.1":{"name":"MiniMax M2.1 (Coding)","dailyUsed":101435,"monthlySpent":505.0000895135148,"dailyCost":16.833336317117162}}}