{"timestamp":1772568600927,"date":"2026-03-03T20:10:00.927Z","models":{"moonshot/kimi-k2.5":{"name":"Moonshot Kimi K2.5 (Primary - ALL BOTS)","dailyUsed":56554,"monthlySpent":291.24750234086355,"dailyCost":9.708250078028785},"kimi-coding/k2p5":{"name":"Kimi Code K2.5 (Sub-agent - ALL BOTS)","dailyUsed":57617,"monthlySpent":286.48586529535146,"dailyCost":9.549528843178383},"minimax/MiniMax-M2.1":{"name":"MiniMax M2.1 (Coding)","dailyUsed":54712,"monthlySpent":267.97235472592354,"dailyCost":8.932411824197452}}}