{"timestamp":1774048800162,"date":"2026-03-20T23:20:00.162Z","models":{"moonshot/kimi-k2.5":{"name":"Moonshot Kimi K2.5 (Primary - ALL BOTS)","dailyUsed":219332,"monthlySpent":1111.5778307434418,"dailyCost":37.052594358114725},"kimi-coding/k2p5":{"name":"Kimi Code K2.5 (Sub-agent - ALL BOTS)","dailyUsed":221520,"monthlySpent":1097.108631015409,"dailyCost":36.57028770051363},"minimax/MiniMax-M2.1":{"name":"MiniMax M2.1 (Coding)","dailyUsed":218304,"monthlySpent":1077.117463638398,"dailyCost":35.90391545461327}}}