{"timestamp":1772591700183,"date":"2026-03-04T02:35:00.183Z","models":{"moonshot/kimi-k2.5":{"name":"Moonshot Kimi K2.5 (Primary - ALL BOTS)","dailyUsed":58865,"monthlySpent":302.68320565479877,"dailyCost":10.089440188493292},"kimi-coding/k2p5":{"name":"Kimi Code K2.5 (Sub-agent - ALL BOTS)","dailyUsed":60242,"monthlySpent":298.19367806405864,"dailyCost":9.939789268801954},"minimax/MiniMax-M2.1":{"name":"MiniMax M2.1 (Coding)","dailyUsed":57000,"monthlySpent":279.5385994303874,"dailyCost":9.317953314346248}}}