{"timestamp":1774005900067,"date":"2026-03-20T11:25:00.067Z","models":{"moonshot/kimi-k2.5":{"name":"Moonshot Kimi K2.5 (Primary - ALL BOTS)","dailyUsed":214504,"monthlySpent":1085.053098312225,"dailyCost":36.168436610407504},"kimi-coding/k2p5":{"name":"Kimi Code K2.5 (Sub-agent - ALL BOTS)","dailyUsed":217094,"monthlySpent":1074.905164724177,"dailyCost":35.83017215747257},"minimax/MiniMax-M2.1":{"name":"MiniMax M2.1 (Coding)","dailyUsed":213591,"monthlySpent":1054.3645343951825,"dailyCost":35.14548447983942}}}