{"timestamp":1773969600417,"date":"2026-03-20T01:20:00.417Z","models":{"moonshot/kimi-k2.5":{"name":"Moonshot Kimi K2.5 (Primary - ALL BOTS)","dailyUsed":210695,"monthlySpent":1066.7025495254156,"dailyCost":35.55675165084719},"kimi-coding/k2p5":{"name":"Kimi Code K2.5 (Sub-agent - ALL BOTS)","dailyUsed":212468,"monthlySpent":1055.7470800071983,"dailyCost":35.19156933357328},"minimax/MiniMax-M2.1":{"name":"MiniMax M2.1 (Coding)","dailyUsed":208936,"monthlySpent":1033.6056822788898,"dailyCost":34.45352274262966}}}