{"timestamp":1773662100078,"date":"2026-03-16T11:55:00.078Z","models":{"moonshot/kimi-k2.5":{"name":"Moonshot Kimi K2.5 (Primary - ALL BOTS)","dailyUsed":176082,"monthlySpent":893.9723533900888,"dailyCost":29.799078446336292},"kimi-coding/k2p5":{"name":"Kimi Code K2.5 (Sub-agent - ALL BOTS)","dailyUsed":178577,"monthlySpent":881.0104773696111,"dailyCost":29.36701591232037},"minimax/MiniMax-M2.1":{"name":"MiniMax M2.1 (Coding)","dailyUsed":174856,"monthlySpent":867.2642991757186,"dailyCost":28.908809972523954}}}