{"timestamp":1772705100864,"date":"2026-03-05T10:05:00.864Z","models":{"moonshot/kimi-k2.5":{"name":"Moonshot Kimi K2.5 (Primary - ALL BOTS)","dailyUsed":71248,"monthlySpent":363.44643247501,"dailyCost":12.114881082500334},"kimi-coding/k2p5":{"name":"Kimi Code K2.5 (Sub-agent - ALL BOTS)","dailyUsed":72849,"monthlySpent":355.83189492424475,"dailyCost":11.861063164141491},"minimax/MiniMax-M2.1":{"name":"MiniMax M2.1 (Coding)","dailyUsed":69791,"monthlySpent":344.0264957904365,"dailyCost":11.467549859681217}}}